remag/__init__.py
remag/__main__.py
remag/_version.py
remag/adaptive_resolution.py
remag/cli.py
remag/clustering.py
remag/core.py
remag/features.py
remag/losses.py
remag/miniprot_utils.py
remag/models.py
remag/output.py
remag/refinement.py
remag/utils.py
remag/db/refseq_db.faa.gz
remag/hyenadna_classifier/__init__.py
remag/hyenadna_classifier/hyenadna_model.py
remag/hyenadna_classifier/predictor.py
remag/hyenadna_classifier/standalone_tokenizer.py
remag/hyenadna_classifier/models/pytorch_model.bin
remag/hyenadna_classifier/models/pytorch_model.bin.20251024
remag-0.3.3.dist-info/licenses/LICENSE
remag-0.3.3.dist-info/METADATA
remag-0.3.3.dist-info/WHEEL
remag-0.3.3.dist-info/entry_points.txt
remag-0.3.3.dist-info/top_level.txt
remag-0.3.3.dist-info/RECORD
