Metadata-Version: 2.4
Name: remag
Version: 0.3.3
Summary: Recovery of high-quality eukaryotic genomes from complex metagenomes
Author-email: Daniel Gómez-Pérez <daniel.gomez-perez@earlham.ac.uk>
Maintainer-email: Daniel Gómez-Pérez <daniel.gomez-perez@earlham.ac.uk>
License-Expression: MIT
Project-URL: Homepage, https://github.com/danielzmbp/remag
Project-URL: Repository, https://github.com/danielzmbp/remag
Project-URL: Documentation, https://github.com/danielzmbp/remag
Project-URL: Bug Tracker, https://github.com/danielzmbp/remag/issues
Keywords: metagenomics,binning,neural networks,contrastive learning,bioinformatics
Classifier: Development Status :: 4 - Beta
Classifier: Intended Audience :: Science/Research
Classifier: Operating System :: OS Independent
Classifier: Programming Language :: Python :: 3
Classifier: Programming Language :: Python :: 3.9
Classifier: Programming Language :: Python :: 3.10
Classifier: Programming Language :: Python :: 3.11
Classifier: Topic :: Scientific/Engineering :: Bio-Informatics
Requires-Python: >=3.9
License-File: LICENSE
Requires-Dist: numpy>=1.21.0
Requires-Dist: pandas>=1.3.0
Requires-Dist: pysam>=0.18.0
Requires-Dist: rich-click>=1.5.0
Requires-Dist: torch>=1.11.0
Requires-Dist: loguru>=0.6.0
Requires-Dist: scikit-learn>=1.0.0
Requires-Dist: tqdm>=4.62.0
Requires-Dist: leidenalg>=0.9.0
Requires-Dist: igraph>=0.10.0
Requires-Dist: einops>=0.6.0
Provides-Extra: plotting
Requires-Dist: matplotlib>=3.5.0; extra == "plotting"
Requires-Dist: umap-learn>=0.5.0; extra == "plotting"
Provides-Extra: dev
Requires-Dist: pytest>=7.0.0; extra == "dev"
Requires-Dist: pytest-cov>=3.0.0; extra == "dev"
Requires-Dist: black>=22.0.0; extra == "dev"
Requires-Dist: isort>=5.10.0; extra == "dev"
Requires-Dist: flake8>=4.0.0; extra == "dev"
Dynamic: license-file
